odoo/addons/sale_product_email/README.rst
odoo/addons/sale_product_email/__init__.py
odoo/addons/sale_product_email/__manifest__.py
odoo/addons/sale_product_email/i18n/sale_product_email.pot
odoo/addons/sale_product_email/models/__init__.py
odoo/addons/sale_product_email/models/product_template.py
odoo/addons/sale_product_email/models/sale_order.py
odoo/addons/sale_product_email/readme/CONTRIBUTORS.rst
odoo/addons/sale_product_email/readme/DESCRIPTION.rst
odoo/addons/sale_product_email/readme/USAGE.rst
odoo/addons/sale_product_email/static/description/icon.png
odoo/addons/sale_product_email/static/description/index.html
odoo/addons/sale_product_email/static/description/mail_template_select.png
odoo/addons/sale_product_email/tests/__init__.py
odoo/addons/sale_product_email/tests/test_sale_product_email.py
odoo/addons/sale_product_email/views/product_template.xml
odoo_addon_sale_product_email-16.0.1.0.0.2.dist-info/METADATA
odoo_addon_sale_product_email-16.0.1.0.0.2.dist-info/WHEEL
odoo_addon_sale_product_email-16.0.1.0.0.2.dist-info/top_level.txt
odoo_addon_sale_product_email-16.0.1.0.0.2.dist-info/RECORD
